arc_agi_llm/__init__.py
arc_agi_llm/models/llm.py
arc_agi_llm/models/cloud/gpt.py
arc_agi_llm-0.0.3.dist-info/METADATA
arc_agi_llm-0.0.3.dist-info/WHEEL
arc_agi_llm-0.0.3.dist-info/RECORD
