Metadata-Version: 2.4
Name: arc-agi-llm
Version: 0.0.3
Requires-Python: >=3.10
Requires-Dist: arc-agi-core
Requires-Dist: dotenv>=0.9.9
Requires-Dist: openai>=1.77.0
